README.txt
setup.py
borg/__init__.py
borg.supergroup.egg-info/PKG-INFO
borg.supergroup.egg-info/SOURCES.txt
borg.supergroup.egg-info/dependency_links.txt
borg.supergroup.egg-info/entry_points.txt
borg.supergroup.egg-info/namespace_packages.txt
borg.supergroup.egg-info/not-zip-safe
borg.supergroup.egg-info/paster_plugins.txt
borg.supergroup.egg-info/requires.txt
borg.supergroup.egg-info/top_level.txt
borg/supergroup/__init__.py
borg/supergroup/config.py
borg/supergroup/configure.zcml
borg/supergroup/integration.txt
borg/supergroup/interfaces.py
borg/supergroup/plugin.py
borg/supergroup/setuphandlers.py
borg/supergroup/tests.py
borg/supergroup/profiles/default/borg.supergroup_various.txt
borg/supergroup/profiles/default/metadata.xml
borg/supergroup/zmi/addSuperGroupProviderForm.pt
docs/HISTORY.txt
docs/INSTALL.txt
docs/LICENSE.GPL
docs/LICENSE.txt