Metadata-Version: 1.0
Name: borg.supergroup
Version: 1.0rc1
Summary: Create groups as if by super
Home-page: http://plone.org
Author: Martin Aspeli
Author-email: optilude@gmail.com
License: LGPL
Keywords: Plone PAS
Platform: UNKNOWN
Classifier: Framework :: Plone
Classifier: Programming Language :: Python
Classifier: Topic :: Software Development :: Libraries :: Python Modules
